django_backoffice/__init__.py
django_backoffice-0.0.1.dev0.dist-info/LICENSE
django_backoffice-0.0.1.dev0.dist-info/METADATA
django_backoffice-0.0.1.dev0.dist-info/WHEEL
django_backoffice-0.0.1.dev0.dist-info/top_level.txt
django_backoffice-0.0.1.dev0.dist-info/RECORD
